Metadata-Version: 1.1
Name: datacoco-secretsmanager
Version: 0.1.3
Summary: Data common code for AWS Secrets Manager by Equinox
Home-page: https://github.com/equinoxfitness/datacoco-secretsmanager
Author: Equinox Fitness
Author-email: UNKNOWN
License: MIT
Platform: UNKNOWN
Classifier: Development Status :: 5 - Production/Stable
Classifier: Intended Audience :: Developers
Classifier: Natural Language :: English
Classifier: License :: OSI Approved :: MIT License
Classifier: Programming Language :: Python :: 3.6
